yfQuotes/__init__.py
yfQuotes/batchquotes/__init__.py
yfQuotes/batchquotes/async_io.py
yfQuotes/batchquotes/multithread.py
yfQuotes/streamquotes/__init__.py
yfQuotes/streamquotes/decoder.py
yfQuotes/streamquotes/streamer.py
yfQuotes/streamquotes/yfinance_pb2.py
yfQuotes/tests/__init__.py
yfQuotes/tests/test_batch.py
yfQuotes/tests/test_stream.py
yfQuotes-0.0.14.dist-info/METADATA
yfQuotes-0.0.14.dist-info/WHEEL
yfQuotes-0.0.14.dist-info/top_level.txt
yfQuotes-0.0.14.dist-info/RECORD
