Metadata-Version: 2.1
Name: yfQuotes
Version: 0.0.14
Summary: get quotes from yahoo!Finance
Home-page: UNKNOWN
Author: Justin Law
Author-email: justin.kklaw@gmail.com
License: UNKNOWN
Platform: UNKNOWN
Classifier: Programming Language :: Python :: 3
Classifier: Operating System :: OS Independent
Requires-Python: >=3.7
Requires-Dist: beautifulsoup4 (==4.9.3)
Requires-Dist: aiohttp (==3.8.1)
Requires-Dist: websocket-client (==1.2.3)
